omnata_plugin_runtime/__init__.py
omnata_plugin_runtime/api.py
omnata_plugin_runtime/configuration.py
omnata_plugin_runtime/forms.py
omnata_plugin_runtime/json_schema.py
omnata_plugin_runtime/logging.py
omnata_plugin_runtime/omnata_plugin.py
omnata_plugin_runtime/plugin_entrypoints.py
omnata_plugin_runtime/rate_limiting.py
omnata_plugin_runtime-0.12.1.dist-info/METADATA
omnata_plugin_runtime-0.12.1.dist-info/WHEEL
omnata_plugin_runtime-0.12.1.dist-info/licenses/LICENSE
omnata_plugin_runtime-0.12.1.dist-info/RECORD
