Metadata-Version: 2.4
Name: omnata-plugin-runtime
Version: 0.12.1
Summary: Classes and common runtime components for building and running Omnata Plugins
License-File: LICENSE
Author: James Weakley
Author-email: james.weakley@omnata.com
Requires-Python: >=3.10,<=3.13
Classifier: Programming Language :: Python :: 3
Classifier: Programming Language :: Python :: 3.10
Classifier: Programming Language :: Python :: 3.11
Classifier: Programming Language :: Python :: 3.12
Classifier: Programming Language :: Python :: 3.13
Requires-Dist: annotated-types (<=0.6.0)
Requires-Dist: certifi (<=2025.1.31)
Requires-Dist: cffi (<=2.0.0)
Requires-Dist: charset-normalizer (<=3.4.4)
Requires-Dist: cryptography (<=46.0.3)
Requires-Dist: filelock (<=3.20.0)
Requires-Dist: idna (<=3.11)
Requires-Dist: jinja2 (>=3.1.2,<=3.1.6)
Requires-Dist: markupsafe (<=3.0.2)
Requires-Dist: numpy (<=2.3.5)
Requires-Dist: opentelemetry-api (<=1.38.0)
Requires-Dist: packaging (<=25.0)
Requires-Dist: pandas (<=2.3.3)
Requires-Dist: platformdirs (<=4.5.0)
Requires-Dist: protobuf (<=6.33.0)
Requires-Dist: pyarrow (<=21.0.0)
Requires-Dist: pycparser (<=2.23)
Requires-Dist: pydantic (>=2,<=2.12.4)
Requires-Dist: pydantic-core (<=2.41.5)
Requires-Dist: pyjwt (<=2.10.1)
Requires-Dist: pyopenssl (<=225.3.0)
Requires-Dist: pytz (<=2025.2)
Requires-Dist: pyyaml (<=6.0.3)
Requires-Dist: requests (>=2,<=2.32.5)
Requires-Dist: setuptools (<=80.9.0)
Requires-Dist: snowflake-connector-python (>=3,<4)
Requires-Dist: snowflake-snowpark-python (>=1.20.0,<=1.43.0)
Requires-Dist: snowflake-telemetry-python (<=0.5.0)
Requires-Dist: tenacity (>=8,<9)
Requires-Dist: tomlkit (<=0.13.3)
Requires-Dist: urllib3 (<=2.5.0)
Requires-Dist: wheel (<=0.45.1)
Requires-Dist: wrapt (<=2.0.1)
